{
  "2025": {
    "code": "2025",
    "sources": [
      "https://theriagames.com/guide/legend-of-mushroom-codes/"
    ],
    "first_seen": "2025-10-24T17:14:30.707Z",
    "last_seen": "2025-10-24T17:14:30.707Z"
  },
  "Moonlight": {
    "code": "Moonlight",
    "sources": [
      "https://www.pockettactics.com/legend-of-mushroom/codes"
    ],
    "first_seen": "2025-10-24T17:14:30.707Z",
    "last_seen": "2025-10-24T17:14:30.707Z"
  },
  "lovespam": {
    "code": "lovespam",
    "sources": [
      "https://www.pocketgamer.com/legend-of-mushroom/codes/"
    ],
    "first_seen": "2025-10-24T17:14:30.707Z",
    "last_seen": "2025-10-24T17:14:30.707Z"
  },
  "meevasgj": {
    "code": "meevasgj",
    "sources": [
      "https://www.pocketgamer.com/legend-of-mushroom/codes/"
    ],
    "first_seen": "2025-10-24T17:14:30.707Z",
    "last_seen": "2025-10-24T17:14:30.707Z"
  },
  "meet6dc7": {
    "code": "meet6dc7",
    "sources": [
      "https://www.pocketgamer.com/legend-of-mushroom/codes/"
    ],
    "first_seen": "2025-10-24T17:14:30.707Z",
    "last_seen": "2025-10-24T17:14:30.707Z"
  },
  "meecepez": {
    "code": "meecepez",
    "sources": [
      "https://www.pocketgamer.com/legend-of-mushroom/codes/"
    ],
    "first_seen": "2025-10-24T17:14:30.707Z",
    "last_seen": "2025-10-24T17:14:30.707Z"
  },
  "meezzv3n": {
    "code": "meezzv3n",
    "sources": [
      "https://www.pocketgamer.com/legend-of-mushroom/codes/"
    ],
    "first_seen": "2025-10-24T17:14:30.707Z",
    "last_seen": "2025-10-24T17:14:30.707Z"
  },
  "meebpatr": {
    "code": "meebpatr",
    "sources": [
      "https://www.pocketgamer.com/legend-of-mushroom/codes/"
    ],
    "first_seen": "2025-10-24T17:14:30.707Z",
    "last_seen": "2025-10-24T17:14:30.707Z"
  },
  "xeo6c6m8": {
    "code": "xeo6c6m8",
    "sources": [
      "https://www.pocketgamer.com/legend-of-mushroom/codes/"
    ],
    "first_seen": "2025-10-24T17:14:30.707Z",
    "last_seen": "2025-10-24T17:14:30.707Z"
  },
  "xeouqj9c": {
    "code": "xeouqj9c",
    "sources": [
      "https://www.pocketgamer.com/legend-of-mushroom/codes/"
    ],
    "first_seen": "2025-10-24T17:14:30.707Z",
    "last_seen": "2025-10-24T17:14:30.707Z"
  },
  "xeo5xzu6": {
    "code": "xeo5xzu6",
    "sources": [
      "https://www.pocketgamer.com/legend-of-mushroom/codes/"
    ],
    "first_seen": "2025-10-24T17:14:30.707Z",
    "last_seen": "2025-10-24T17:14:30.707Z"
  },
  "xeoru6e4": {
    "code": "xeoru6e4",
    "sources": [
      "https://www.pocketgamer.com/legend-of-mushroom/codes/"
    ],
    "first_seen": "2025-10-24T17:14:30.707Z",
    "last_seen": "2025-10-24T17:14:30.707Z"
  },
  "xeoznyez": {
    "code": "xeoznyez",
    "sources": [
      "https://www.pocketgamer.com/legend-of-mushroom/codes/"
    ],
    "first_seen": "2025-10-24T17:14:30.707Z",
    "last_seen": "2025-10-24T17:14:30.707Z"
  },
  "xeove8dn": {
    "code": "xeove8dn",
    "sources": [
      "https://www.pocketgamer.com/legend-of-mushroom/codes/"
    ],
    "first_seen": "2025-10-24T17:14:30.707Z",
    "last_seen": "2025-10-24T17:14:30.707Z"
  },
  "xeoafr83": {
    "code": "xeoafr83",
    "sources": [
      "https://www.pocketgamer.com/legend-of-mushroom/codes/"
    ],
    "first_seen": "2025-10-24T17:14:30.707Z",
    "last_seen": "2025-10-24T17:14:30.707Z"
  },
  "xeouthgk": {
    "code": "xeouthgk",
    "sources": [
      "https://www.pocketgamer.com/legend-of-mushroom/codes/"
    ],
    "first_seen": "2025-10-24T17:14:30.707Z",
    "last_seen": "2025-10-24T17:14:30.707Z"
  },
  "xeogbfy3": {
    "code": "xeogbfy3",
    "sources": [
      "https://www.pocketgamer.com/legend-of-mushroom/codes/"
    ],
    "first_seen": "2025-10-24T17:14:30.707Z",
    "last_seen": "2025-10-24T17:14:30.707Z"
  },
  "xeoztt77": {
    "code": "xeoztt77",
    "sources": [
      "https://www.pocketgamer.com/legend-of-mushroom/codes/"
    ],
    "first_seen": "2025-10-24T17:14:30.707Z",
    "last_seen": "2025-10-24T17:14:30.707Z"
  },
  "xeostcu9": {
    "code": "xeostcu9",
    "sources": [
      "https://www.pocketgamer.com/legend-of-mushroom/codes/"
    ],
    "first_seen": "2025-10-24T17:14:30.707Z",
    "last_seen": "2025-10-24T17:14:30.707Z"
  },
  "xeohqne6": {
    "code": "xeohqne6",
    "sources": [
      "https://www.pocketgamer.com/legend-of-mushroom/codes/"
    ],
    "first_seen": "2025-10-24T17:14:30.707Z",
    "last_seen": "2025-10-24T17:14:30.707Z"
  },
  "xeomji3x": {
    "code": "xeomji3x",
    "sources": [
      "https://www.pocketgamer.com/legend-of-mushroom/codes/"
    ],
    "first_seen": "2025-10-24T17:14:30.707Z",
    "last_seen": "2025-10-24T17:14:30.707Z"
  },
  "xeofuzyd": {
    "code": "xeofuzyd",
    "sources": [
      "https://www.pocketgamer.com/legend-of-mushroom/codes/"
    ],
    "first_seen": "2025-10-24T17:14:30.707Z",
    "last_seen": "2025-10-24T17:14:30.707Z"
  },
  "xeop3849": {
    "code": "xeop3849",
    "sources": [
      "https://www.pocketgamer.com/legend-of-mushroom/codes/"
    ],
    "first_seen": "2025-10-24T17:14:30.707Z",
    "last_seen": "2025-10-24T17:14:30.707Z"
  },
  "xeokwrir": {
    "code": "xeokwrir",
    "sources": [
      "https://www.pocketgamer.com/legend-of-mushroom/codes/"
    ],
    "first_seen": "2025-10-24T17:14:30.707Z",
    "last_seen": "2025-10-24T17:14:30.707Z"
  },
  "xeove2wh": {
    "code": "xeove2wh",
    "sources": [
      "https://www.pocketgamer.com/legend-of-mushroom/codes/"
    ],
    "first_seen": "2025-10-24T17:14:30.707Z",
    "last_seen": "2025-10-24T17:14:30.707Z"
  },
  "xeork3vy": {
    "code": "xeork3vy",
    "sources": [
      "https://www.pocketgamer.com/legend-of-mushroom/codes/"
    ],
    "first_seen": "2025-10-24T17:14:30.707Z",
    "last_seen": "2025-10-24T17:14:30.707Z"
  },
  "xeoqt4ab": {
    "code": "xeoqt4ab",
    "sources": [
      "https://www.pocketgamer.com/legend-of-mushroom/codes/"
    ],
    "first_seen": "2025-10-24T17:14:30.707Z",
    "last_seen": "2025-10-24T17:14:30.707Z"
  },
  "xeop2awt": {
    "code": "xeop2awt",
    "sources": [
      "https://www.pocketgamer.com/legend-of-mushroom/codes/"
    ],
    "first_seen": "2025-10-24T17:14:30.707Z",
    "last_seen": "2025-10-24T17:14:30.707Z"
  },
  "xeo4u6xm": {
    "code": "xeo4u6xm",
    "sources": [
      "https://www.pocketgamer.com/legend-of-mushroom/codes/"
    ],
    "first_seen": "2025-10-24T17:14:30.707Z",
    "last_seen": "2025-10-24T17:14:30.707Z"
  },
  "xeoakaw5": {
    "code": "xeoakaw5",
    "sources": [
      "https://www.pocketgamer.com/legend-of-mushroom/codes/"
    ],
    "first_seen": "2025-10-24T17:14:30.707Z",
    "last_seen": "2025-10-24T17:14:30.707Z"
  },
  "xeozft32": {
    "code": "xeozft32",
    "sources": [
      "https://www.pocketgamer.com/legend-of-mushroom/codes/"
    ],
    "first_seen": "2025-10-24T17:14:30.707Z",
    "last_seen": "2025-10-24T17:14:30.707Z"
  },
  "xeoe8jr9": {
    "code": "xeoe8jr9",
    "sources": [
      "https://www.pocketgamer.com/legend-of-mushroom/codes/"
    ],
    "first_seen": "2025-10-24T17:14:30.707Z",
    "last_seen": "2025-10-24T17:14:30.707Z"
  },
  "xeox7fq8": {
    "code": "xeox7fq8",
    "sources": [
      "https://www.pocketgamer.com/legend-of-mushroom/codes/"
    ],
    "first_seen": "2025-10-24T17:14:30.707Z",
    "last_seen": "2025-10-24T17:14:30.707Z"
  },
  "xeod4spa": {
    "code": "xeod4spa",
    "sources": [
      "https://www.pocketgamer.com/legend-of-mushroom/codes/"
    ],
    "first_seen": "2025-10-24T17:14:30.707Z",
    "last_seen": "2025-10-24T17:14:30.707Z"
  },
  "xeo53krf": {
    "code": "xeo53krf",
    "sources": [
      "https://www.pocketgamer.com/legend-of-mushroom/codes/"
    ],
    "first_seen": "2025-10-24T17:14:30.707Z",
    "last_seen": "2025-10-24T17:14:30.707Z"
  },
  "xeok2v9f": {
    "code": "xeok2v9f",
    "sources": [
      "https://www.pocketgamer.com/legend-of-mushroom/codes/"
    ],
    "first_seen": "2025-10-24T17:14:30.707Z",
    "last_seen": "2025-10-24T17:14:30.707Z"
  },
  "xeomt9kh": {
    "code": "xeomt9kh",
    "sources": [
      "https://www.pocketgamer.com/legend-of-mushroom/codes/"
    ],
    "first_seen": "2025-10-24T17:14:30.707Z",
    "last_seen": "2025-10-24T17:14:30.707Z"
  },
  "HOPE": {
    "code": "HOPE",
    "sources": [
      "https://www.pocketgamer.com/legend-of-mushroom/codes/"
    ],
    "first_seen": "2025-10-24T17:14:30.707Z",
    "last_seen": "2025-10-24T17:14:30.707Z"
  },
  "SHROOM": {
    "code": "SHROOM",
    "sources": [
      "https://www.pocketgamer.com/legend-of-mushroom/codes/"
    ],
    "first_seen": "2025-10-24T17:14:30.707Z",
    "last_seen": "2025-10-24T17:14:30.707Z"
  },
  "CAKE": {
    "code": "CAKE",
    "sources": [
      "https://www.pocketgamer.com/legend-of-mushroom/codes/"
    ],
    "first_seen": "2025-10-24T17:14:30.707Z",
    "last_seen": "2025-10-24T17:14:30.707Z"
  },
  "Mushmyth": {
    "code": "Mushmyth",
    "sources": [
      "https://www.pocketgamer.com/legend-of-mushroom/codes/"
    ],
    "first_seen": "2025-10-24T17:14:30.707Z",
    "last_seen": "2025-10-24T17:14:30.707Z"
  },
  "WOMAN": {
    "code": "WOMAN",
    "sources": [
      "https://www.pocketgamer.com/legend-of-mushroom/codes/"
    ],
    "first_seen": "2025-10-24T17:14:30.707Z",
    "last_seen": "2025-10-24T17:14:30.707Z"
  },
  "contest": {
    "code": "contest",
    "sources": [
      "https://www.pocketgamer.com/legend-of-mushroom/codes/"
    ],
    "first_seen": "2025-10-24T17:14:30.707Z",
    "last_seen": "2025-10-24T17:14:30.707Z"
  },
  "firework": {
    "code": "firework",
    "sources": [
      "https://www.pocketgamer.com/legend-of-mushroom/codes/"
    ],
    "first_seen": "2025-10-24T17:14:30.707Z",
    "last_seen": "2025-10-24T17:14:30.707Z"
  },
  "Hi2025": {
    "code": "Hi2025",
    "sources": [
      "https://www.pocketgamer.com/legend-of-mushroom/codes/"
    ],
    "first_seen": "2025-10-24T17:14:30.707Z",
    "last_seen": "2025-10-24T17:14:30.707Z"
  },
  "happy2025": {
    "code": "happy2025",
    "sources": [
      "https://www.pocketgamer.com/legend-of-mushroom/codes/"
    ],
    "first_seen": "2025-10-24T17:14:30.707Z",
    "last_seen": "2025-10-24T17:14:30.707Z"
  },
  "Destiny": {
    "code": "Destiny",
    "sources": [
      "https://www.pocketgamer.com/legend-of-mushroom/codes/"
    ],
    "first_seen": "2025-10-24T17:14:30.707Z",
    "last_seen": "2025-10-24T17:14:30.707Z"
  },
  "starship": {
    "code": "starship",
    "sources": [
      "https://www.pocketgamer.com/legend-of-mushroom/codes/"
    ],
    "first_seen": "2025-10-24T17:14:30.707Z",
    "last_seen": "2025-10-24T17:14:30.707Z"
  },
  "teacher": {
    "code": "teacher",
    "sources": [
      "https://www.pocketgamer.com/legend-of-mushroom/codes/"
    ],
    "first_seen": "2025-10-24T17:14:30.707Z",
    "last_seen": "2025-10-24T17:14:30.707Z"
  },
  "Beast": {
    "code": "Beast",
    "sources": [
      "https://www.pocketgamer.com/legend-of-mushroom/codes/"
    ],
    "first_seen": "2025-10-24T17:14:30.707Z",
    "last_seen": "2025-10-24T17:14:30.707Z"
  },
  "mushstar": {
    "code": "mushstar",
    "sources": [
      "https://www.pocketgamer.com/legend-of-mushroom/codes/"
    ],
    "first_seen": "2025-10-24T17:14:30.707Z",
    "last_seen": "2025-10-24T17:14:30.707Z"
  },
  "champion": {
    "code": "champion",
    "sources": [
      "https://www.pocketgamer.com/legend-of-mushroom/codes/"
    ],
    "first_seen": "2025-10-24T17:14:30.707Z",
    "last_seen": "2025-10-24T17:14:30.707Z"
  },
  "summer": {
    "code": "summer",
    "sources": [
      "https://www.pocketgamer.com/legend-of-mushroom/codes/"
    ],
    "first_seen": "2025-10-24T17:14:30.707Z",
    "last_seen": "2025-10-24T17:14:30.707Z"
  },
  "8b3a7r": {
    "code": "8b3a7r",
    "sources": [
      "https://www.pocketgamer.com/legend-of-mushroom/codes/"
    ],
    "first_seen": "2025-10-24T17:14:30.707Z",
    "last_seen": "2025-10-24T17:14:30.707Z"
  },
  "arabic": {
    "code": "arabic",
    "sources": [
      "https://www.pocketgamer.com/legend-of-mushroom/codes/"
    ],
    "first_seen": "2025-10-24T17:14:30.707Z",
    "last_seen": "2025-10-24T17:14:30.707Z"
  },
  "swim": {
    "code": "swim",
    "sources": [
      "https://www.pocketgamer.com/legend-of-mushroom/codes/"
    ],
    "first_seen": "2025-10-24T17:14:30.707Z",
    "last_seen": "2025-10-24T17:14:30.707Z"
  },
  "ducky": {
    "code": "ducky",
    "sources": [
      "https://www.pocketgamer.com/legend-of-mushroom/codes/"
    ],
    "first_seen": "2025-10-24T17:14:30.707Z",
    "last_seen": "2025-10-24T17:14:30.707Z"
  },
  "flypepe": {
    "code": "flypepe",
    "sources": [
      "https://www.pocketgamer.com/legend-of-mushroom/codes/"
    ],
    "first_seen": "2025-10-24T17:14:30.707Z",
    "last_seen": "2025-10-24T17:14:30.707Z"
  },
  "peperoom": {
    "code": "peperoom",
    "sources": [
      "https://www.pocketgamer.com/legend-of-mushroom/codes/"
    ],
    "first_seen": "2025-10-24T17:14:30.707Z",
    "last_seen": "2025-10-24T17:14:30.707Z"
  },
  "bunny": {
    "code": "bunny",
    "sources": [
      "https://www.pocketgamer.com/legend-of-mushroom/codes/"
    ],
    "first_seen": "2025-10-24T17:14:30.707Z",
    "last_seen": "2025-10-24T17:14:30.707Z"
  },
  "creator": {
    "code": "creator",
    "sources": [
      "https://www.pocketgamer.com/legend-of-mushroom/codes/"
    ],
    "first_seen": "2025-10-24T17:14:30.707Z",
    "last_seen": "2025-10-24T17:14:30.707Z"
  },
  "gatling": {
    "code": "gatling",
    "sources": [
      "https://www.pocketgamer.com/legend-of-mushroom/codes/"
    ],
    "first_seen": "2025-10-24T17:14:30.707Z",
    "last_seen": "2025-10-24T17:14:30.707Z"
  },
  "lom1777": {
    "code": "lom1777",
    "sources": [
      "https://www.pocketgamer.com/legend-of-mushroom/codes/"
    ],
    "first_seen": "2025-10-24T17:14:30.707Z",
    "last_seen": "2025-10-24T17:14:30.707Z"
  },
  "lom7777": {
    "code": "lom7777",
    "sources": [
      "https://www.pocketgamer.com/legend-of-mushroom/codes/"
    ],
    "first_seen": "2025-10-24T17:14:30.707Z",
    "last_seen": "2025-10-24T17:14:30.707Z"
  },
  "lomvip": {
    "code": "lomvip",
    "sources": [
      "https://www.pocketgamer.com/legend-of-mushroom/codes/"
    ],
    "first_seen": "2025-10-24T17:14:30.707Z",
    "last_seen": "2025-10-24T17:14:30.707Z"
  },
  "lom2024": {
    "code": "lom2024",
    "sources": [
      "https://www.pocketgamer.com/legend-of-mushroom/codes/"
    ],
    "first_seen": "2025-10-24T17:14:30.707Z",
    "last_seen": "2025-10-24T17:14:30.707Z"
  },
  "topmush": {
    "code": "topmush",
    "sources": [
      "https://www.pocketgamer.com/legend-of-mushroom/codes/"
    ],
    "first_seen": "2025-10-24T17:14:30.707Z",
    "last_seen": "2025-10-24T17:14:30.707Z"
  },
  "thankyou": {
    "code": "thankyou",
    "sources": [
      "https://www.pocketgamer.com/legend-of-mushroom/codes/"
    ],
    "first_seen": "2025-10-24T17:14:30.707Z",
    "last_seen": "2025-10-24T17:14:30.707Z"
  },
  "welcome": {
    "code": "welcome",
    "sources": [
      "https://www.pocketgamer.com/legend-of-mushroom/codes/"
    ],
    "first_seen": "2025-10-24T17:14:30.707Z",
    "last_seen": "2025-10-24T17:14:30.707Z"
  },
  "Elements": {
    "code": "Elements",
    "sources": [
      "https://www.pocketgamer.com/legend-of-mushroom/codes/"
    ],
    "first_seen": "2025-10-24T17:14:30.707Z",
    "last_seen": "2025-10-24T17:14:30.707Z"
  },
  "Firework": {
    "code": "Firework",
    "sources": [
      "https://www.pockettactics.com/legend-of-mushroom/codes"
    ],
    "first_seen": "2025-10-24T17:14:30.707Z",
    "last_seen": "2025-10-24T17:14:30.707Z"
  },
  "star": {
    "code": "star",
    "sources": [
      "https://www.pockettactics.com/legend-of-mushroom/codes"
    ],
    "first_seen": "2025-10-24T17:14:30.707Z",
    "last_seen": "2025-10-24T17:14:30.707Z"
  },
  "NICE": {
    "code": "NICE",
    "sources": [
      "https://www.pockettactics.com/legend-of-mushroom/codes"
    ],
    "first_seen": "2025-10-24T17:14:30.707Z",
    "last_seen": "2025-10-24T17:14:30.707Z"
  },
  "sunshine": {
    "code": "sunshine",
    "sources": [
      "https://www.pockettactics.com/legend-of-mushroom/codes"
    ],
    "first_seen": "2025-10-24T17:14:30.707Z",
    "last_seen": "2025-10-24T17:14:30.707Z"
  },
  "Hero": {
    "code": "Hero",
    "sources": [
      "https://www.pockettactics.com/legend-of-mushroom/codes"
    ],
    "first_seen": "2025-10-24T17:14:30.707Z",
    "last_seen": "2025-10-24T17:14:30.707Z"
  },
  "COOL": {
    "code": "COOL",
    "sources": [
      "https://www.pockettactics.com/legend-of-mushroom/codes"
    ],
    "first_seen": "2025-10-24T17:14:30.707Z",
    "last_seen": "2025-10-24T17:14:30.707Z"
  },
  "power": {
    "code": "power",
    "sources": [
      "https://www.pockettactics.com/legend-of-mushroom/codes"
    ],
    "first_seen": "2025-10-24T17:14:30.707Z",
    "last_seen": "2025-10-24T17:14:30.707Z"
  },
  "HOT": {
    "code": "HOT",
    "sources": [
      "https://www.pockettactics.com/legend-of-mushroom/codes"
    ],
    "first_seen": "2025-10-24T17:14:30.707Z",
    "last_seen": "2025-10-24T17:14:30.707Z"
  },
  "cyber": {
    "code": "cyber",
    "sources": [
      "https://www.pockettactics.com/legend-of-mushroom/codes"
    ],
    "first_seen": "2025-10-24T17:14:30.707Z",
    "last_seen": "2025-10-24T17:14:30.707Z"
  },
  "brave": {
    "code": "brave",
    "sources": [
      "https://www.pockettactics.com/legend-of-mushroom/codes"
    ],
    "first_seen": "2025-10-24T17:14:30.707Z",
    "last_seen": "2025-10-24T17:14:30.707Z"
  },
  "RSS": {
    "code": "RSS",
    "sources": [
      "https://www.pockettactics.com/legend-of-mushroom/codes"
    ],
    "first_seen": "2025-10-24T17:14:30.707Z",
    "last_seen": "2025-10-24T17:14:30.707Z"
  },
  "Summer": {
    "code": "Summer",
    "sources": [
      "https://www.pockettactics.com/legend-of-mushroom/codes"
    ],
    "first_seen": "2025-10-24T17:14:30.707Z",
    "last_seen": "2025-10-24T17:14:30.707Z"
  },
  "Racing": {
    "code": "Racing",
    "sources": [
      "https://www.pockettactics.com/legend-of-mushroom/codes"
    ],
    "first_seen": "2025-10-24T17:14:30.707Z",
    "last_seen": "2025-10-24T17:14:30.707Z"
  },
  "Journey": {
    "code": "Journey",
    "sources": [
      "https://www.pockettactics.com/legend-of-mushroom/codes"
    ],
    "first_seen": "2025-10-24T17:14:30.707Z",
    "last_seen": "2025-10-24T17:14:30.707Z"
  },
  "Dreaming": {
    "code": "Dreaming",
    "sources": [
      "https://www.pockettactics.com/legend-of-mushroom/codes"
    ],
    "first_seen": "2025-10-24T17:14:30.707Z",
    "last_seen": "2025-10-24T17:14:30.707Z"
  },
  "Shroomie": {
    "code": "Shroomie",
    "sources": [
      "https://www.pockettactics.com/legend-of-mushroom/codes"
    ],
    "first_seen": "2025-10-24T17:14:30.707Z",
    "last_seen": "2025-10-24T17:14:30.707Z"
  },
  "pixel": {
    "code": "pixel",
    "sources": [
      "https://www.pockettactics.com/legend-of-mushroom/codes"
    ],
    "first_seen": "2025-10-24T17:14:30.707Z",
    "last_seen": "2025-10-24T17:14:30.707Z"
  },
  "happyfarm": {
    "code": "happyfarm",
    "sources": [
      "https://www.pockettactics.com/legend-of-mushroom/codes"
    ],
    "first_seen": "2025-10-24T17:14:30.707Z",
    "last_seen": "2025-10-24T17:14:30.707Z"
  },
  "Adventure": {
    "code": "Adventure",
    "sources": [
      "https://www.pockettactics.com/legend-of-mushroom/codes"
    ],
    "first_seen": "2025-10-24T17:14:30.707Z",
    "last_seen": "2025-10-24T17:14:30.707Z"
  },
  "LOL4U": {
    "code": "LOL4U",
    "sources": [
      "https://www.pockettactics.com/legend-of-mushroom/codes"
    ],
    "first_seen": "2025-10-24T17:14:30.707Z",
    "last_seen": "2025-10-24T17:14:30.707Z"
  },
  "Easter": {
    "code": "Easter",
    "sources": [
      "https://www.pockettactics.com/legend-of-mushroom/codes"
    ],
    "first_seen": "2025-10-24T17:14:30.707Z",
    "last_seen": "2025-10-24T17:14:30.707Z"
  },
  "EidJoy": {
    "code": "EidJoy",
    "sources": [
      "https://www.pockettactics.com/legend-of-mushroom/codes"
    ],
    "first_seen": "2025-10-24T17:14:30.707Z",
    "last_seen": "2025-10-24T17:14:30.707Z"
  },
  "Magical": {
    "code": "Magical",
    "sources": [
      "https://www.pockettactics.com/legend-of-mushroom/codes"
    ],
    "first_seen": "2025-10-24T17:14:30.707Z",
    "last_seen": "2025-10-24T17:14:30.707Z"
  },
  "Unicorn": {
    "code": "Unicorn",
    "sources": [
      "https://www.pockettactics.com/legend-of-mushroom/codes"
    ],
    "first_seen": "2025-10-24T17:14:30.707Z",
    "last_seen": "2025-10-24T17:14:30.707Z"
  },
  "Feb222": {
    "code": "Feb222",
    "sources": [
      "https://www.pockettactics.com/legend-of-mushroom/codes"
    ],
    "first_seen": "2025-10-24T17:14:30.707Z",
    "last_seen": "2025-10-24T17:14:30.707Z"
  },
  "Darkmyth": {
    "code": "Darkmyth",
    "sources": [
      "https://www.pockettactics.com/legend-of-mushroom/codes"
    ],
    "first_seen": "2025-10-24T17:14:30.707Z",
    "last_seen": "2025-10-24T17:14:30.707Z"
  },
  "newpvp": {
    "code": "newpvp",
    "sources": [
      "https://www.pockettactics.com/legend-of-mushroom/codes"
    ],
    "first_seen": "2025-10-24T17:14:30.707Z",
    "last_seen": "2025-10-24T17:14:30.707Z"
  },
  "Loveu": {
    "code": "Loveu",
    "sources": [
      "https://www.pockettactics.com/legend-of-mushroom/codes"
    ],
    "first_seen": "2025-10-24T17:14:30.707Z",
    "last_seen": "2025-10-24T17:14:30.707Z"
  },
  "LunarNY": {
    "code": "LunarNY",
    "sources": [
      "https://www.pockettactics.com/legend-of-mushroom/codes"
    ],
    "first_seen": "2025-10-24T17:14:30.707Z",
    "last_seen": "2025-10-24T17:14:30.707Z"
  },
  "Ancient": {
    "code": "Ancient",
    "sources": [
      "https://www.pockettactics.com/legend-of-mushroom/codes"
    ],
    "first_seen": "2025-10-24T17:14:30.707Z",
    "last_seen": "2025-10-24T17:14:30.707Z"
  },
  "2Future": {
    "code": "2Future",
    "sources": [
      "https://www.pockettactics.com/legend-of-mushroom/codes"
    ],
    "first_seen": "2025-10-24T17:14:30.707Z",
    "last_seen": "2025-10-24T17:14:30.707Z"
  },
  "santa": {
    "code": "santa",
    "sources": [
      "https://www.pockettactics.com/legend-of-mushroom/codes"
    ],
    "first_seen": "2025-10-24T17:14:30.707Z",
    "last_seen": "2025-10-24T17:14:30.707Z"
  },
  "icemaze": {
    "code": "icemaze",
    "sources": [
      "https://www.pockettactics.com/legend-of-mushroom/codes"
    ],
    "first_seen": "2025-10-24T17:14:30.707Z",
    "last_seen": "2025-10-24T17:14:30.707Z"
  },
  "snowball": {
    "code": "snowball",
    "sources": [
      "https://www.pockettactics.com/legend-of-mushroom/codes"
    ],
    "first_seen": "2025-10-24T17:14:30.707Z",
    "last_seen": "2025-10-24T17:14:30.707Z"
  },
  "chillout": {
    "code": "chillout",
    "sources": [
      "https://www.pockettactics.com/legend-of-mushroom/codes"
    ],
    "first_seen": "2025-10-24T17:14:30.707Z",
    "last_seen": "2025-10-24T17:14:30.707Z"
  },
  "Snow": {
    "code": "Snow",
    "sources": [
      "https://www.pockettactics.com/legend-of-mushroom/codes"
    ],
    "first_seen": "2025-10-24T17:14:30.707Z",
    "last_seen": "2025-10-24T17:14:30.707Z"
  },
  "2024Xmas": {
    "code": "2024Xmas",
    "sources": [
      "https://www.pockettactics.com/legend-of-mushroom/codes"
    ],
    "first_seen": "2025-10-24T17:14:30.707Z",
    "last_seen": "2025-10-24T17:14:30.707Z"
  },
  "Thanks": {
    "code": "Thanks",
    "sources": [
      "https://www.pockettactics.com/legend-of-mushroom/codes"
    ],
    "first_seen": "2025-10-24T17:14:30.707Z",
    "last_seen": "2025-10-24T17:14:30.707Z"
  },
  "Mona": {
    "code": "Mona",
    "sources": [
      "https://www.pockettactics.com/legend-of-mushroom/codes"
    ],
    "first_seen": "2025-10-24T17:14:30.707Z",
    "last_seen": "2025-10-24T17:14:30.707Z"
  },
  "Davi": {
    "code": "Davi",
    "sources": [
      "https://www.pockettactics.com/legend-of-mushroom/codes"
    ],
    "first_seen": "2025-10-24T17:14:30.707Z",
    "last_seen": "2025-10-24T17:14:30.707Z"
  },
  "pumpkin": {
    "code": "pumpkin",
    "sources": [
      "https://www.pockettactics.com/legend-of-mushroom/codes"
    ],
    "first_seen": "2025-10-24T17:14:30.707Z",
    "last_seen": "2025-10-24T17:14:30.707Z"
  },
  "vampire": {
    "code": "vampire",
    "sources": [
      "https://www.pockettactics.com/legend-of-mushroom/codes"
    ],
    "first_seen": "2025-10-24T17:14:30.707Z",
    "last_seen": "2025-10-24T17:14:30.707Z"
  },
  "Q2R8M0": {
    "code": "Q2R8M0",
    "sources": [
      "https://www.pockettactics.com/legend-of-mushroom/codes"
    ],
    "first_seen": "2025-10-24T17:14:30.707Z",
    "last_seen": "2025-10-24T17:14:30.707Z"
  },
  "A3B7D2": {
    "code": "A3B7D2",
    "sources": [
      "https://www.pockettactics.com/legend-of-mushroom/codes"
    ],
    "first_seen": "2025-10-24T17:14:30.707Z",
    "last_seen": "2025-10-24T17:14:30.707Z"
  },
  "J8K4L6": {
    "code": "J8K4L6",
    "sources": [
      "https://www.pockettactics.com/legend-of-mushroom/codes"
    ],
    "first_seen": "2025-10-24T17:14:30.707Z",
    "last_seen": "2025-10-24T17:14:30.707Z"
  },
  "X5Y9H1": {
    "code": "X5Y9H1",
    "sources": [
      "https://www.pockettactics.com/legend-of-mushroom/codes"
    ],
    "first_seen": "2025-10-24T17:14:30.707Z",
    "last_seen": "2025-10-24T17:14:30.707Z"
  },
  "Galaxy": {
    "code": "Galaxy",
    "sources": [
      "https://www.pockettactics.com/legend-of-mushroom/codes"
    ],
    "first_seen": "2025-10-24T17:14:30.707Z",
    "last_seen": "2025-10-24T17:14:30.707Z"
  },
  "Halfyear": {
    "code": "Halfyear",
    "sources": [
      "https://www.pockettactics.com/legend-of-mushroom/codes"
    ],
    "first_seen": "2025-10-24T17:14:30.707Z",
    "last_seen": "2025-10-24T17:14:30.707Z"
  },
  "panda": {
    "code": "panda",
    "sources": [
      "https://www.pockettactics.com/legend-of-mushroom/codes"
    ],
    "first_seen": "2025-10-24T17:14:30.707Z",
    "last_seen": "2025-10-24T17:14:30.707Z"
  },
  "tiger96": {
    "code": "tiger96",
    "sources": [
      "https://www.pockettactics.com/legend-of-mushroom/codes"
    ],
    "first_seen": "2025-10-24T17:14:30.707Z",
    "last_seen": "2025-10-24T17:14:30.707Z"
  },
  "music123": {
    "code": "music123",
    "sources": [
      "https://www.pockettactics.com/legend-of-mushroom/codes"
    ],
    "first_seen": "2025-10-24T17:14:30.707Z",
    "last_seen": "2025-10-24T17:14:30.707Z"
  },
  "C2P1Q5": {
    "code": "C2P1Q5",
    "sources": [
      "https://www.pockettactics.com/legend-of-mushroom/codes"
    ],
    "first_seen": "2025-10-24T17:14:30.707Z",
    "last_seen": "2025-10-24T17:14:30.707Z"
  },
  "5F8W2D": {
    "code": "5F8W2D",
    "sources": [
      "https://www.pockettactics.com/legend-of-mushroom/codes"
    ],
    "first_seen": "2025-10-24T17:14:30.707Z",
    "last_seen": "2025-10-24T17:14:30.707Z"
  },
  "merge": {
    "code": "merge",
    "sources": [
      "https://www.pockettactics.com/legend-of-mushroom/codes"
    ],
    "first_seen": "2025-10-24T17:14:30.707Z",
    "last_seen": "2025-10-24T17:14:30.707Z"
  },
  "warship": {
    "code": "warship",
    "sources": [
      "https://www.pockettactics.com/legend-of-mushroom/codes"
    ],
    "first_seen": "2025-10-24T17:14:30.707Z",
    "last_seen": "2025-10-24T17:14:30.707Z"
  },
  "x2y8zp": {
    "code": "x2y8zp",
    "sources": [
      "https://www.pockettactics.com/legend-of-mushroom/codes"
    ],
    "first_seen": "2025-10-24T17:14:30.707Z",
    "last_seen": "2025-10-24T17:14:30.707Z"
  },
  "dream": {
    "code": "dream",
    "sources": [
      "https://www.pockettactics.com/legend-of-mushroom/codes"
    ],
    "first_seen": "2025-10-24T17:14:30.707Z",
    "last_seen": "2025-10-24T17:14:30.707Z"
  },
  "7asb4c": {
    "code": "7asb4c",
    "sources": [
      "https://www.pockettactics.com/legend-of-mushroom/codes"
    ],
    "first_seen": "2025-10-24T17:14:30.707Z",
    "last_seen": "2025-10-24T17:14:30.707Z"
  },
  "mumum": {
    "code": "mumum",
    "sources": [
      "https://www.pockettactics.com/legend-of-mushroom/codes"
    ],
    "first_seen": "2025-10-24T17:14:30.707Z",
    "last_seen": "2025-10-24T17:14:30.707Z"
  },
  "lovemush": {
    "code": "lovemush",
    "sources": [
      "https://www.pockettactics.com/legend-of-mushroom/codes"
    ],
    "first_seen": "2025-10-24T17:14:30.707Z",
    "last_seen": "2025-10-24T17:14:30.707Z"
  },
  "dc200k": {
    "code": "dc200k",
    "sources": [
      "https://www.pockettactics.com/legend-of-mushroom/codes"
    ],
    "first_seen": "2025-10-24T17:14:30.707Z",
    "last_seen": "2025-10-24T17:14:30.707Z"
  },
  "happy51": {
    "code": "happy51",
    "sources": [
      "https://www.pockettactics.com/legend-of-mushroom/codes"
    ],
    "first_seen": "2025-10-24T17:14:30.707Z",
    "last_seen": "2025-10-24T17:14:30.707Z"
  },
  "lobaac": {
    "code": "lobaac",
    "sources": [
      "https://www.pockettactics.com/legend-of-mushroom/codes"
    ],
    "first_seen": "2025-10-24T17:14:30.707Z",
    "last_seen": "2025-10-24T17:14:30.707Z"
  },
  "happyeid": {
    "code": "happyeid",
    "sources": [
      "https://www.pockettactics.com/legend-of-mushroom/codes"
    ],
    "first_seen": "2025-10-24T17:14:30.707Z",
    "last_seen": "2025-10-24T17:14:30.707Z"
  },
  "hlwjtg": {
    "code": "hlwjtg",
    "sources": [
      "https://www.pockettactics.com/legend-of-mushroom/codes"
    ],
    "first_seen": "2025-10-24T17:14:30.707Z",
    "last_seen": "2025-10-24T17:14:30.707Z"
  },
  "1xutpj": {
    "code": "1xutpj",
    "sources": [
      "https://www.pockettactics.com/legend-of-mushroom/codes"
    ],
    "first_seen": "2025-10-24T17:14:30.707Z",
    "last_seen": "2025-10-24T17:14:30.707Z"
  },
  "Relics": {
    "code": "Relics",
    "sources": [
      "https://theriagames.com/guide/legend-of-mushroom-codes/"
    ],
    "first_seen": "2025-10-24T17:14:30.707Z",
    "last_seen": "2025-10-24T17:14:30.707Z"
  }
}